{
  "key": "ECC-9455",
  "issue_type": "Portfolio Epic",
  "title": "DOM0202 OnNet Security - Fixed Business DSL / Glasfaser Pro",
  "status": "Funnel",
  "description": "",
  "business_value": {},
  "assignee": "Unassigned",
  "priority": "",
  "target_start": "2025-10-01",
  "target_end": "2026-05-31",
  "fix_versions": [],
  "acceptance_criteria": [],
  "components": [
    {
      "code": "Prima+",
      "title": "Prima+ "
    }
  ],
  "labels": [],
  "realized_by": [
    {
      "key": "ECC-9456",
      "title": "ECC-9456",
      "summary": "DOM0202 OnNet Security - Fixed CompanyFlex",
      "url": "https://jira.telekom.de/browse/ECC-9456",
      "relation_type": "child"
    }
  ],
  "child_issues": [],
  "attachments": []
}